opsys_gimbal_controller/__init__.py
opsys_gimbal_controller/gimbal_abstract.py
opsys_gimbal_controller/gimbal_controller.py
opsys_gimbal_controller/gimbal_types.py
opsys_gimbal_controller/newmark/__init__.py
opsys_gimbal_controller/newmark/gclib.dll
opsys_gimbal_controller/newmark/gclib.py
opsys_gimbal_controller/newmark/gclibo.dll
opsys_gimbal_controller/newmark/libcrypto-1_1-x64.dll
opsys_gimbal_controller/newmark/libssl-1_1-x64.dll
opsys_gimbal_controller/newmark/newmark_controller.py
opsys_gimbal_controller/thorlabs/Thorlabs.MotionControl.Benchtop.StepperMotor.dll
opsys_gimbal_controller/thorlabs/Thorlabs.MotionControl.DeviceManager.dll
opsys_gimbal_controller/thorlabs/__init__.py
opsys_gimbal_controller/thorlabs/_utils.py
opsys_gimbal_controller/thorlabs/benchtop_stepper_motor.py
opsys_gimbal_controller/thorlabs/thorlabs_controller.py
opsys_gimbal_controller-0.0.4.dist-info/LICENSE
opsys_gimbal_controller-0.0.4.dist-info/METADATA
opsys_gimbal_controller-0.0.4.dist-info/WHEEL
opsys_gimbal_controller-0.0.4.dist-info/top_level.txt
opsys_gimbal_controller-0.0.4.dist-info/RECORD
