Metadata-Version: 2.1
Name: opsys-gimbal-controller
Version: 0.0.4
Summary: python package for gimbal devices control
Home-page: https://bitbucket.org/opsys_tech/opsys-gimbal-controller/src/master/
Download-URL: https://bitbucket.org/opsys_tech/opsys-gimbal-controller/src/master/
Author: dmitry.borovensky
Author-email: dmitry.borovensky@opsys-tech.com
License-File: LICENSE
